Metadata-Version: 2.1
Name: truncnorm
Version: 0.0.1
Summary: Moments for doubly truncated multivariate normal distributions
Author: Jaakko Luttinen
Author-email: jaakko.luttinen@iki.fi
Project-URL: Homepage, https://github.com/jluttine/truncnorm
Project-URL: Download, https://pypi.org/project/truncnorm/
Project-URL: Bug reports, https://github.com/jluttine/truncnorm/issues
Project-URL: Contributing, https://github.com/jluttine/truncnorm/pulls
Classifier: Programming Language :: Python :: 3 :: Only
Classifier: Development Status :: 3 - Alpha
Classifier: Environment :: Console
Classifier: Intended Audience :: Developers
Classifier: License :: OSI Approved :: MIT License
Classifier: Operating System :: OS Independent
Classifier: Programming Language :: Python :: 3 :: Only
Classifier: Topic :: Scientific/Engineering
Classifier: Topic :: Software Development :: Libraries
License-File: LICENSE
Requires-Dist: numpy
Requires-Dist: scipy
